src/__init__.py
src/config_loader.py
simpleConfigManager-0.1.0.dist-info/LICENSE
simpleConfigManager-0.1.0.dist-info/METADATA
simpleConfigManager-0.1.0.dist-info/WHEEL
simpleConfigManager-0.1.0.dist-info/top_level.txt
simpleConfigManager-0.1.0.dist-info/RECORD
