Metadata-Version: 2.1
Name: simpleConfigManager
Version: 0.1.0
Summary: A simple configuration management library
Home-page: UNKNOWN
Author: Adapala Bharadwaj
Author-email: bharadwajadapala28@gmail.com
License: UNKNOWN
Platform: UNKNOWN
Classifier: Programming Language :: Python :: 3
Classifier: License :: OSI Approved :: MIT License
Classifier: Operating System :: OS Independent
Requires-Python: >=3.6
License-File: LICENSE
